LICENSE
MANIFEST.in
README.md
setup.py
django_unical_bootstrap_italia/__init__.py
django_unical_bootstrap_italia/apps.py
django_unical_bootstrap_italia.egg-info/PKG-INFO
django_unical_bootstrap_italia.egg-info/SOURCES.txt
django_unical_bootstrap_italia.egg-info/dependency_links.txt
django_unical_bootstrap_italia.egg-info/requires.txt
django_unical_bootstrap_italia.egg-info/top_level.txt
django_unical_bootstrap_italia/static/css/unical-style.css
django_unical_bootstrap_italia/static/images/logo.svg
django_unical_bootstrap_italia/static/images/logo1.svg
django_unical_bootstrap_italia/static/images/logo_back.svg
django_unical_bootstrap_italia/static/images/logo_white.png
django_unical_bootstrap_italia/static/images/unical_banner.jpg
django_unical_bootstrap_italia/static/images/unical_logo.svg
django_unical_bootstrap_italia/static/images/favicon/README.md
django_unical_bootstrap_italia/static/images/favicon/favicon-32x32.png
django_unical_bootstrap_italia/templates/404.html
django_unical_bootstrap_italia/templates/500.html
django_unical_bootstrap_italia/templates/base-setup.html
django_unical_bootstrap_italia/templates/error-page.html
django_unical_bootstrap_italia/templates/index.html