Metadata-Version: 2.1
Name: django-unical-bootstrap-italia
Version: 1.2.0
Summary: Django theme for Università della Calabria (UNICAL) based on Bootstrap Italia theme
Home-page: https://github.com/UniversitaDellaCalabria/django-unical-bootstrap-italia
Author: Giuseppe De Marco, Francesco Filicetti
Author-email: giuseppe.demarco@unical.it, francesco.filicetti@unical.it
License: Apache 2.0
Platform: UNKNOWN
Classifier: Environment :: Web Environment
Classifier: Framework :: Django
Classifier: Framework :: Django :: 2.0
Classifier: Framework :: Django :: 3.0
Classifier: Framework :: Django :: 4.0
Classifier: Intended Audience :: Developers
Classifier: License :: OSI Approved :: Apache Software License
Classifier: Operating System :: OS Independent
Classifier: Programming Language :: Python
Classifier: Programming Language :: Python :: 3
